qbindiff/__init__.py
qbindiff/__main__.py
qbindiff/abstract.py
qbindiff/differ.py
qbindiff/exceptions.py
qbindiff/types.py
qbindiff/version.py
qbindiff/visitor.py
qbindiff/features/__init__.py
qbindiff/features/artefact.py
qbindiff/features/extractor.py
qbindiff/features/graph.py
qbindiff/features/manager.py
qbindiff/features/mnemonic.py
qbindiff/features/topology.py
qbindiff/features/wlgk.py
qbindiff/loader/__init__.py
qbindiff/loader/basic_block.py
qbindiff/loader/data.py
qbindiff/loader/function.py
qbindiff/loader/instruction.py
qbindiff/loader/operand.py
qbindiff/loader/program.py
qbindiff/loader/structure.py
qbindiff/loader/types.py
qbindiff/loader/backend/__init__.py
qbindiff/loader/backend/abstract.py
qbindiff/loader/backend/binexport.py
qbindiff/loader/backend/ida.py
qbindiff/loader/backend/quokka.py
qbindiff/loader/backend/utils.py
qbindiff/mapping/__init__.py
qbindiff/mapping/bindiff.py
qbindiff/mapping/mapping.py
qbindiff/matcher/__init__.py
qbindiff/matcher/belief_propagation.py
qbindiff/matcher/matcher.py
qbindiff/matcher/squares.cpython-310-i386-linux-gnu.so
qbindiff/passes/__init__.py
qbindiff/passes/base.py
qbindiff/passes/fast_metrics.cpython-310-i386-linux-gnu.so
qbindiff/passes/metrics.py
qbindiff/passes/passes.py
qbindiff/passes/utils.py
qbindiff/utils/__init__.py
qbindiff/utils/openmp_helpers.cpython-310-i386-linux-gnu.so
qbindiff/utils/utils.py
qbindiff.libs/libgcc_s-887de51c.so.1
qbindiff.libs/libgomp-24921df4.so.1.0.0
qbindiff.libs/libstdc++-d6415257.so.6.0.33
qbindiff-1.2.3.dist-info/METADATA
qbindiff-1.2.3.dist-info/WHEEL
qbindiff-1.2.3.dist-info/entry_points.txt
qbindiff-1.2.3.dist-info/RECORD
