Metadata-Version: 2.1
Name: qbindiff
Version: 1.2.3
Summary: QBindiff binary diffing tool based on a Network Alignment problem
Author-Email: Quarkslab <diffing@quarkslab.com>
License: Apache Software License (Apache License, Version 2)
Project-URL: Homepage, https://github.com/quarkslab/qbindiff
Project-URL: Repository, https://github.com/quarkslab/qbindiff
Project-URL: Documentation, https://github.com/quarkslab/qbindiff
Requires-Python: >=3.10
Requires-Dist: rich-click
Requires-Dist: numpy
Requires-Dist: scipy
Requires-Dist: lapjv-numpy2; sys_platform == "linux" or sys_platform == "windows"
Requires-Dist: lapx; sys_platform != "linux" and sys_platform != "windows"
Requires-Dist: networkx
Requires-Dist: capstone>=5.0.1
Requires-Dist: datasketch
Requires-Dist: scikit-learn
Requires-Dist: python-louvain
Requires-Dist: enum_tools
Requires-Dist: python-bindiff>=0.3.1
Requires-Dist: python-binexport>=0.3.2
Requires-Dist: quokka-project
Requires-Dist: idascript
Provides-Extra: doc
Requires-Dist: sphinx>=7.2.0; extra == "doc"
Requires-Dist: sphinx-design; extra == "doc"
Requires-Dist: sphinx-rtd-theme>=1.3; extra == "doc"
Requires-Dist: enum-tools[sphinx]; extra == "doc"
Requires-Dist: sphinx_autodoc_typehints; extra == "doc"
Provides-Extra: dev
Requires-Dist: tox; extra == "dev"
Requires-Dist: pypcode; extra == "dev"
